transformer_tricks.py
transformer_tricks-0.3.4.dist-info/METADATA
transformer_tricks-0.3.4.dist-info/WHEEL
transformer_tricks-0.3.4.dist-info/licenses/LICENSE
transformer_tricks-0.3.4.dist-info/RECORD
