Metadata-Version: 2.4
Name: transformer-tricks
Version: 0.3.4
Summary: A collection of tricks to speed up LLMs, see our transformer-tricks papers on arXiv
Project-URL: Homepage, https://github.com/OpenMachine-ai/transformer-tricks
Project-URL: Bug Tracker, https://github.com/OpenMachine-ai/transformer-tricks/issues
Author-email: Open Machine <info@openmachine.ai>
License-File: LICENSE
Classifier: License :: OSI Approved :: MIT License
Classifier: Operating System :: OS Independent
Classifier: Programming Language :: Python :: 3
Requires-Python: >=3.11
Requires-Dist: accelerate>=1.7.0
Requires-Dist: datasets>=3.6.0
Requires-Dist: transformers>=4.52.3
